walpy/__init__.py
walpy/r_importer.py
walpy/suppress.py
walpy/write_run.py
walpy-2.0.3.dist-info/LICENCE.txt
walpy-2.0.3.dist-info/METADATA
walpy-2.0.3.dist-info/WHEEL
walpy-2.0.3.dist-info/top_level.txt
walpy-2.0.3.dist-info/RECORD
