Metadata-Version: 2.1
Name: walpy
Version: 2.0.3
Summary: General functions
Home-page: https://github.com/walterverwer/walpy
Author: Walter Verwer
Author-email: walterverwer@gmail.com
License: MIT
Download-URL: https://github.com/walterverwer/walpy/archive/refs/tags/v_0.1.tar.gz
Keywords: SOME,MEANINGFULL,KEYWORDS
Platform: UNKNOWN
Classifier: Development Status :: 3 - Alpha
Classifier: Intended Audience :: Developers
Classifier: Topic :: Software Development :: Build Tools
Classifier: License :: OSI Approved :: MIT License
Classifier: Programming Language :: Python :: 3
Classifier: Programming Language :: Python :: 3.4
Classifier: Programming Language :: Python :: 3.5
Classifier: Programming Language :: Python :: 3.6
Requires-Dist: rpy2
Requires-Dist: IPython
